PyOpenColorIO/libOpenColorIO.dylib
PyOpenColorIO/command_line.py
PyOpenColorIO/__init__.py
PyOpenColorIO/PyOpenColorIO.so
PyOpenColorIO/bin/ocioarchive
PyOpenColorIO/bin/ociocheck
PyOpenColorIO/bin/ociobakelut
PyOpenColorIO/bin/ociomergeconfigs
PyOpenColorIO/bin/ociolutimage
PyOpenColorIO/bin/ociochecklut
PyOpenColorIO/bin/ociomakeclf
PyOpenColorIO/bin/ocioperf
PyOpenColorIO/bin/ociowrite
PyOpenColorIO/bin/ocioconvert
PyOpenColorIO/bin/ociodisplay
PyOpenColorIO/bin/ociocpuinfo
PyOpenColorIO/bin/pyocioamf/config-aces-reference.yaml
PyOpenColorIO/bin/pyocioamf/README.md
PyOpenColorIO/bin/pyocioamf/example.amf
PyOpenColorIO/bin/pyocioamf/example_referenced_lut.clf
PyOpenColorIO/bin/pyocioamf/pyocioamf.py
PyOpenColorIO/bin/pyociodisplay/pyociodisplay.py
PyOpenColorIO/bin/pyociodisplay/requirements.txt
PyOpenColorIO/bin/pyociodisplay/README.md
opencolorio-2.5.1.dist-info/RECORD
opencolorio-2.5.1.dist-info/WHEEL
opencolorio-2.5.1.dist-info/entry_points.txt
opencolorio-2.5.1.dist-info/top_level.txt
opencolorio-2.5.1.dist-info/METADATA
opencolorio-2.5.1.dist-info/licenses/LICENSE
