Metadata-Version: 2.4
Name: opencolorio
Version: 2.5.1
Summary: OpenColorIO (OCIO) is a complete color management solution geared towards motion picture production with an emphasis on visual effects and computer animation.
Home-page: https://opencolorio.org/
Author: OpenColorIO Developers
Author-email: ocio-dev@lists.aswf.io
License: Copyright Contributors to the OpenColorIO Project.
Classifier: Development Status :: 5 - Production/Stable
Classifier: Intended Audience :: Developers
Classifier: Topic :: Software Development :: Libraries :: Python Modules
Classifier: Programming Language :: C++
Classifier: Programming Language :: Python :: 3
Classifier: Programming Language :: Python :: 3.9
Classifier: Programming Language :: Python :: 3.10
Classifier: Programming Language :: Python :: 3.11
Classifier: Programming Language :: Python :: 3.12
Classifier: Programming Language :: Python :: 3.13
Classifier: Programming Language :: Python :: 3.14
Classifier: Programming Language :: Python :: Implementation :: CPython
Classifier: Programming Language :: C++
License-File: LICENSE
Dynamic: license-file
